actl/__init__.py
actl/__main__.py
actl/application.py
actl/loader.py
actl/log.py
actl/main.py
actl/singleton.py
actl/version.py
actl/actl-cli/commands/run.py
tests/test_version.py
actl-0.1.0.dist-info/LICENSE
actl-0.1.0.dist-info/METADATA
actl-0.1.0.dist-info/WHEEL
actl-0.1.0.dist-info/entry_points.txt
actl-0.1.0.dist-info/top_level.txt
actl-0.1.0.dist-info/RECORD
