Metadata-Version: 2.1
Name: actl
Version: 0.1.0
Summary: A Python Application Development Framework
Home-page: https://github.com/webplane/actl
Author: João Pinto
Author-email: lamego.pinto@gmail.com
License: MIT
Platform: UNKNOWN
License-File: LICENSE
Requires-Dist: eprint
Requires-Dist: click
